asaniczka/__init__.py
asaniczka/db_tools.py
asaniczka/main.py
asaniczka/scrape_helper.py
asaniczka-3.1.4.dist-info/METADATA
asaniczka-3.1.4.dist-info/WHEEL
asaniczka-3.1.4.dist-info/top_level.txt
asaniczka-3.1.4.dist-info/RECORD
